tee_table.py
tee_table/__init__.py
tee_table/tee_table.py
tee_table-1.0.1.dev1.dist-info/DESCRIPTION.rst
tee_table-1.0.1.dev1.dist-info/METADATA
tee_table-1.0.1.dev1.dist-info/RECORD
tee_table-1.0.1.dev1.dist-info/WHEEL
tee_table-1.0.1.dev1.dist-info/metadata.json
tee_table-1.0.1.dev1.dist-info/top_level.txt
